function_scheduling_distributed_framework/__init__.py
function_scheduling_distributed_framework/constant.py
function_scheduling_distributed_framework/frame_config.py
function_scheduling_distributed_framework/helpers.py
function_scheduling_distributed_framework/set_frame_config.py
function_scheduling_distributed_framework/concurrent_pool/__init__.py
function_scheduling_distributed_framework/concurrent_pool/async_helper.py
function_scheduling_distributed_framework/concurrent_pool/async_pool_executor.py
function_scheduling_distributed_framework/concurrent_pool/bounded_processpoolexcutor.py
function_scheduling_distributed_framework/concurrent_pool/bounded_threadpoolexcutor.py
function_scheduling_distributed_framework/concurrent_pool/concurrent_pool_with_multi_process.py
function_scheduling_distributed_framework/concurrent_pool/custom_evenlet_pool_executor.py
function_scheduling_distributed_framework/concurrent_pool/custom_gevent_pool_executor.py
function_scheduling_distributed_framework/concurrent_pool/custom_threadpool_executor.py
function_scheduling_distributed_framework/concurrent_pool/custom_threadpool_executor000.py
function_scheduling_distributed_framework/concurrent_pool/single_thread_executor.py
function_scheduling_distributed_framework/consumers/__init__.py
function_scheduling_distributed_framework/consumers/base_consumer.py
function_scheduling_distributed_framework/consumers/confirm_mixin.py
function_scheduling_distributed_framework/consumers/http_consumer.py
function_scheduling_distributed_framework/consumers/http_consumer000.py
function_scheduling_distributed_framework/consumers/httpsqs_consumer.py
function_scheduling_distributed_framework/consumers/kafka_consumer.py
function_scheduling_distributed_framework/consumers/kafka_consumer_manually_commit.py
function_scheduling_distributed_framework/consumers/kombu_consumer.py
function_scheduling_distributed_framework/consumers/local_python_queue_consumer.py
function_scheduling_distributed_framework-13.1.dist-info/LICENSE
function_scheduling_distributed_framework-13.1.dist-info/METADATA
function_scheduling_distributed_framework-13.1.dist-info/WHEEL
function_scheduling_distributed_framework-13.1.dist-info/top_level.txt
function_scheduling_distributed_framework-13.1.dist-info/RECORD
