Metadata-Version: 2.1
Name: function-scheduling-distributed-framework
Version: 13.1
Summary: function scheduling distributed framework,support threading,gevent,eventlet,asyncio concurrent,support all kinds of message queue,and has manay control way
Home-page: https://github.com/ydf0509/distributed_framework
Author: bfzs
Author-email: ydf0509@sohu.com
Maintainer: ydf
Maintainer-email: ydf0509@sohu.com
License: BSD License
Keywords: distributed-framework,function-scheduling,rabbitmq,rocketmq,kafka,nsq,redis,disk,sqlachemy,consume-confirm,timing,task-scheduling,apscheduler,pulsar,mqtt,kombu
Platform: all
Classifier: Development Status :: 4 - Beta
Classifier: Operating System :: OS Independent
Classifier: Intended Audience :: Developers
Classifier: License :: OSI Approved :: BSD License
Classifier: Programming Language :: Python
Classifier: Programming Language :: Python :: Implementation
Classifier: Programming Language :: Python :: 3.6
Classifier: Programming Language :: Python :: 3.7
Classifier: Programming Language :: Python :: 3.8
Classifier: Programming Language :: Python :: 3.9
Classifier: Topic :: Software Development :: Libraries
Requires-Dist: eventlet (==0.31.0)
Requires-Dist: gevent (==21.1.2)
Requires-Dist: pymongo (==3.5.1)
Requires-Dist: AMQPStorm (==2.7.1)
Requires-Dist: rabbitpy (==2.0.1)
Requires-Dist: decorator (==4.4.0)
Requires-Dist: Flask
Requires-Dist: flask-bootstrap
Requires-Dist: flask-wtf
Requires-Dist: wtforms
Requires-Dist: flask-login
Requires-Dist: tomorrow3 (==1.1.0)
Requires-Dist: persist-queue (>=0.4.2)
Requires-Dist: elasticsearch
Requires-Dist: kafka-python (==1.4.6)
Requires-Dist: requests
Requires-Dist: gnsq (==1.0.1)
Requires-Dist: psutil
Requires-Dist: sqlalchemy (==1.3.10)
Requires-Dist: sqlalchemy-utils (==0.36.1)
Requires-Dist: apscheduler (==3.7.0)
Requires-Dist: pikav0
Requires-Dist: pikav1
Requires-Dist: redis2
Requires-Dist: redis3
Requires-Dist: redis
Requires-Dist: nb-log (>=6.4)
Requires-Dist: rocketmq
Requires-Dist: zmq
Requires-Dist: pyzmq
Requires-Dist: kombu
Requires-Dist: paho-mqtt
Requires-Dist: setuptools-rust
Requires-Dist: fabric2 (==2.6.0)
Requires-Dist: nats-python
Requires-Dist: nb-filelock
